{
  "project_info": {
    "project_number": "952997310244",
    "project_id": "app-pesquis-satisf-mumbuca",
    "storage_bucket": "app-pesquis-satisf-mumbuca.appspot.com"
  },
  "client": [
    {
      "client_info": {
        "mobilesdk_app_id": "1:952997310244:android:17349e74f3033f3e5d0db1",
        "android_client_info": {
          "package_name": "com.example.appmumbuca"
        }
      },
      "oauth_client": [
        {
          "client_id": "952997310244-v77pasl1jg2kbs4oj8fgtacu1fmdilb8.apps.googleusercontent.com",
          "client_type": 3
        }
      ],
      "api_key": [
        {
          "current_key": "AIzaSyC4VLJLH0AjBh1hI4yYvifNMBQbSU4c2OE"
        }
      ],
      "services": {
        "appinvite_service": {
          "other_platform_oauth_client": [
            {
              "client_id": "952997310244-v77pasl1jg2kbs4oj8fgtacu1fmdilb8.apps.googleusercontent.com",
              "client_type": 3
            }
          ]
        }
      }
    }
  ],
  "configuration_version": "1"
}